ffun/__init__.py
ffun/api/__init__.py
ffun/api/spa/__init__.py
ffun/api/spa/entities.py
ffun/api/spa/front_events.py
ffun/api/spa/http_handlers.py
ffun/api/spa/settings.py
ffun/application/__init__.py
ffun/application/application.py
ffun/application/errors.py
ffun/application/resources.py
ffun/application/settings.py
ffun/application/tests/__init__.py
ffun/application/tests/test_settings.py
ffun/application/user_settings.py
ffun/application/utils.py
ffun/application/workers.py
ffun/auth/__init__.py
ffun/auth/dependencies.py
ffun/auth/domain.py
ffun/auth/errors.py
ffun/auth/idps/__init__.py
ffun/auth/idps/keycloak.py
ffun/auth/idps/no_idp.py
ffun/auth/idps/plugin.py
ffun/auth/settings.py
ffun/auth/tests/__init__.py
ffun/auth/tests/fixtures.py
ffun/auth/tests/test_dependencies.py
ffun/auth/tests/test_domain.py
ffun/cli/__init__.py
ffun/cli/application.py
ffun/cli/cli.py
ffun/cli/commands/__init__.py
ffun/cli/commands/cleaner.py
ffun/cli/commands/configs.py
ffun/cli/commands/entries.py
ffun/cli/commands/estimates.py
ffun/cli/commands/experiments.py
ffun/cli/commands/failed_entries.py
ffun/cli/commands/fixtures.py
ffun/cli/commands/metrics.py
ffun/cli/commands/processors_quality.py
ffun/cli/commands/profile.py
ffun/cli/commands/user_settings.py
ffun/cli/commands/users.py
ffun/cli/commands/workers.py
ffun/cli/commands/yoyo.py
ffun/conftest.py
ffun/core/__init__.py
ffun/core/api.py
ffun/core/background_tasks.py
ffun/core/entities.py
ffun/core/errors.py
ffun/core/json.py
ffun/core/logging.py
ffun/core/metrics.py
ffun/core/middlewares.py
ffun/core/migrations.py
ffun/core/postgresql.py
ffun/core/register.py
ffun/core/sentry.py
ffun/core/settings.py
ffun/core/tests/__init__.py
ffun/core/tests/helpers.py
ffun/core/tests/make.py
ffun/core/tests/test_logging.py
ffun/core/tests/test_metrics.py
ffun/core/tests/test_middlewares.py
ffun/core/utils.py
ffun/data_protection/__init__.py
ffun/data_protection/domain.py
ffun/data_protection/tests/__init__.py
ffun-1.22.4.dist-info/METADATA
ffun-1.22.4.dist-info/WHEEL
ffun-1.22.4.dist-info/entry_points.txt
ffun-1.22.4.dist-info/RECORD
